embeddedML/__init__.py
embeddedML/k_means.py
embeddedML/knn.py
embeddedML/knn_fast.py
embeddedML/logistic_regression.py
embeddedML/logistic_regression_fast.py
embeddedML/metrics.py
embeddedML/multiple_linear_regression.py
embeddedML/multiple_linear_regression_fast.py
embeddedML/naive_bayes.py
embeddedML/naive_bayes_fast.py
embeddedML/pca.py
embeddedML/polynominal_regression.py
embeddedML/polynominal_regression_fast.py
embeddedML/preprocessing.py
embeddedML/simple_linear_regression.py
embeddedML/simple_linear_regression_fast.py
embeddedML/svm.py
embeddedML/svm_fast.py
embeddedml-0.1.7.dist-info/METADATA
embeddedml-0.1.7.dist-info/WHEEL
embeddedml-0.1.7.dist-info/top_level.txt
embeddedml-0.1.7.dist-info/RECORD
